README.md
setup.py
dynamics365/__init__.py
dynamics365.egg-info/PKG-INFO
dynamics365.egg-info/SOURCES.txt
dynamics365.egg-info/dependency_links.txt
dynamics365.egg-info/not-zip-safe
dynamics365.egg-info/requires.txt
dynamics365.egg-info/top_level.txt