Metadata-Version: 1.0
Name: dynamics365
Version: 0.1
Summary: Python Dynamics API Connector
Home-page: https://github.com/wuttem
Author: Matthias Wutte
Author-email: matthias.wutte@gmail.com
License: UNKNOWN
Keywords: dynamics
Platform: UNKNOWN
